aocs_lab/__init__.py
aocs_lab/atmosphere.py
aocs_lab/disturb_torque.py
aocs_lab/inertia_matrix.py
aocs_lab/orbit.py
aocs_lab/sun_time.py
aocs_lab/file/csv_file.py
aocs_lab/influxdb/__init__.py
aocs_lab/influxdb/influxdb1.py
aocs_lab/influxdb/influxdb2.py
aocs_lab/pyIGRF14/.gitignore
aocs_lab/pyIGRF14/CITATION
aocs_lab/pyIGRF14/LICENCE.txt
aocs_lab/pyIGRF14/README.md
aocs_lab/pyIGRF14/__init__.py
aocs_lab/pyIGRF14/acknowledgements.md
aocs_lab/pyIGRF14/environment.yml
aocs_lab/pyIGRF14/igrf.py
aocs_lab/pyIGRF14/igrf_utils.py
aocs_lab/pyIGRF14/io_options.py
aocs_lab/pyIGRF14/pyIGRF.py
aocs_lab/pyIGRF14/requirements.txt
aocs_lab/pyIGRF14/SHC_files/IGRF1.SHC
aocs_lab/pyIGRF14/SHC_files/IGRF10.SHC
aocs_lab/pyIGRF14/SHC_files/IGRF11.SHC
aocs_lab/pyIGRF14/SHC_files/IGRF12.SHC
aocs_lab/pyIGRF14/SHC_files/IGRF13.SHC
aocs_lab/pyIGRF14/SHC_files/IGRF14.SHC
aocs_lab/pyIGRF14/SHC_files/IGRF2.SHC
aocs_lab/pyIGRF14/SHC_files/IGRF3.SHC
aocs_lab/pyIGRF14/SHC_files/IGRF4.SHC
aocs_lab/pyIGRF14/SHC_files/IGRF5.SHC
aocs_lab/pyIGRF14/SHC_files/IGRF6.SHC
aocs_lab/pyIGRF14/SHC_files/IGRF7.SHC
aocs_lab/pyIGRF14/SHC_files/IGRF8.SHC
aocs_lab/pyIGRF14/SHC_files/IGRF9.SHC
aocs_lab/pyIGRF14/tests/tests_igrf13.py
aocs_lab/pyIGRF14/tests/tests_igrf14.py
aocs_lab/spacetrack/tle.py
aocs_lab/utils/__init__.py
aocs_lab/utils/astro.py
aocs_lab/utils/constants.py
aocs_lab/utils/lib.py
aocs_lab/utils/time.py
aocs_lab/wheel/__init__.py
aocs_lab/wheel/wheel_data_process.py
aocs_lab-0.0.15.dist-info/METADATA
aocs_lab-0.0.15.dist-info/WHEEL
aocs_lab-0.0.15.dist-info/licenses/LICENSE
aocs_lab-0.0.15.dist-info/RECORD
