Metadata-Version: 2.4
Name: aocs_lab
Version: 0.0.15
Summary: 姿轨控工具箱
Author-email: wz <wzhmwz@gmail.com>
License-File: LICENSE
Classifier: License :: OSI Approved :: MIT License
Classifier: Operating System :: OS Independent
Classifier: Programming Language :: Python :: 3
Requires-Python: >=3.8
Requires-Dist: astropy>=5.2.2
Requires-Dist: influxdb-client
Requires-Dist: matplotlib
Requires-Dist: numpy
Requires-Dist: pymsis>=0.7.0
Requires-Dist: requests
Requires-Dist: scipy
